themex/__init__.py
themex/llm_runner/__init__.py
themex/llm_runner/direct_runner.py
themex/llm_runner/langchain_runner.py
themex/llm_runner/schema.py
themex/llm_runner/utils.py
themex/logger.py
themex/paths.py
themex/prompts/system_prompt.txt
themex/prompts/theming_sentiment.txt
themex/utils.py
themex-0.1.0a1.post3.dist-info/METADATA
themex-0.1.0a1.post3.dist-info/WHEEL
themex-0.1.0a1.post3.dist-info/licenses/LICENSE
themex-0.1.0a1.post3.dist-info/RECORD
