Metadata-Version: 2.4
Name: themex
Version: 0.1.0a1.post3
Summary: A theme extraction tool using LLMs
License: MIT
License-File: LICENSE
Author: Yanhua Xu
Author-email: 19346059+alysiayx@users.noreply.github.com
Requires-Python: >=3.12,<3.13
Classifier: License :: OSI Approved :: MIT License
Classifier: Programming Language :: Python :: 3
Classifier: Programming Language :: Python :: 3.12
Requires-Dist: accelerate (>=1.5.2,<2.0.0)
Requires-Dist: anthropic (>=0.49.0,<0.50.0)
Requires-Dist: azure-ai-textanalytics (>=5.3.0,<6.0.0)
Requires-Dist: ipykernel (>=6.29.5,<7.0.0)
Requires-Dist: json-repair (>=0.41.1,<0.42.0)
Requires-Dist: jsonfinder (>=0.4.2,<0.5.0)
Requires-Dist: jsonpointer (>=3.0.0,<4.0.0)
Requires-Dist: langchain (>=0.3.23,<0.4.0)
Requires-Dist: langchain-community (>=0.3.21,<0.4.0)
Requires-Dist: langchain-core (>=0.3.54,<0.4.0)
Requires-Dist: llama-cpp-python (>=0.3.8,<0.4.0)
Requires-Dist: matplotlib (>=3.10.1,<4.0.0)
Requires-Dist: nbformat (>=5.10.4,<6.0.0)
Requires-Dist: nltk (>=3.9.1,<4.0.0)
Requires-Dist: openai (>=1.68.2,<2.0.0)
Requires-Dist: openpyxl (>=3.1.5,<4.0.0)
Requires-Dist: pandas (>=2.2.3,<3.0.0)
Requires-Dist: plotly (>=6.0.1,<7.0.0)
Requires-Dist: pydantic (>=2.11.3,<3.0.0)
Requires-Dist: python-dotenv (>=1.1.0,<2.0.0)
Requires-Dist: scikit-learn (>=1.6.1,<2.0.0)
Requires-Dist: sentencepiece (>=0.2.0,<0.3.0)
Requires-Dist: spacy (>=3.8.4,<4.0.0)
Requires-Dist: tensorflow (>=2.19.0,<3.0.0)
Requires-Dist: tf-keras (>=2.19.0,<3.0.0)
Requires-Dist: torch (>=2.6.0,<3.0.0)
Requires-Dist: transformers (>=4.52.4,<5.0.0)
Requires-Dist: wordcloud (>=1.9.4,<2.0.0)
